mlx_lm_lens/__init__.py
mlx_lm_lens/_version.py
mlx_lm_lens/lens.py
mlx_lm_lens/lm_lens.py
mlx_lm_lens-0.0.1.dist-info/licenses/LICENSE
mlx_lm_lens-0.0.1.dist-info/METADATA
mlx_lm_lens-0.0.1.dist-info/WHEEL
mlx_lm_lens-0.0.1.dist-info/top_level.txt
mlx_lm_lens-0.0.1.dist-info/RECORD
