Metadata-Version: 2.4
Name: mlx-lm-lens
Version: 0.0.1
Summary: Find the hidden meaning of LLMs
Home-page: https://github.com/Goekdeniz-Guelmez/mlx-lm-lens
Author: Gökdeniz Gülmez
Author-email: goekdenizguelmez@gmail.com
License: Apache
Requires-Python: >=3.12
License-File: LICENSE
Requires-Dist: mlx-lm>=0.25.1
Requires-Dist: mlx>=0.26.1
Dynamic: author
Dynamic: author-email
Dynamic: description
Dynamic: description-content-type
Dynamic: home-page
Dynamic: license
Dynamic: license-file
Dynamic: requires-dist
Dynamic: requires-python
Dynamic: summary
